{
  "collapse-filter": false,
  "search": "",
  "showTags": false,
  "showAttachments": false,
  "hideUnresolved": false,
  "showOrphans": true,
  "collapse-color-groups": true,
  "colorGroups": [
    {
      "query": "",
      "color": {
        "a": 1,
        "rgb": 14069084
      }
    }
  ],
  "collapse-display": false,
  "showArrow": true,
  "textFadeMultiplier": -3,
  "nodeSizeMultiplier": 0.916666666666667,
  "lineSizeMultiplier": 3.51979166666667,
  "collapse-forces": false,
  "centerStrength": 0,
  "repelStrength": 0,
  "linkStrength": 0,
  "linkDistance": 30,
  "scale": 0.2517227099848538,
  "close": true
}